vulfocus_client_api/__init__.py
vulfocus_client_api/hostEntity.py
vulfocus_client_api/imageEntity.py
vulfocus_client_api/operationConstants.py
vulfocus_client_api/vulfocusClient.py
vulfocus_client_api/vulfocusException.py
VulfocusSdk-0.0.1.dist-info/LICENSE
VulfocusSdk-0.0.1.dist-info/METADATA
VulfocusSdk-0.0.1.dist-info/WHEEL
VulfocusSdk-0.0.1.dist-info/top_level.txt
VulfocusSdk-0.0.1.dist-info/RECORD
