Metadata-Version: 2.1
Name: VulfocusSdk
Version: 0.0.1
Summary: The Api for vulfocus
Home-page: https://github.com/fofapro/vulfocus-py
Author: x98zy
Author-email: xu1580987871@163.com
License: UNKNOWN
Project-URL: Bug Tracker, https://github.com/fofapro/vulfocus-py/issues
Platform: UNKNOWN
Classifier: Programming Language :: Python :: 3
Classifier: License :: OSI Approved :: MIT License
Classifier: Operating System :: OS Independent
License-File: LICENSE
